torchtnt/__init__.py
torchtnt/py.typed
torchtnt/framework/__init__.py
torchtnt/framework/_callback_handler.py
torchtnt/framework/_loop_utils.py
torchtnt/framework/_test_utils.py
torchtnt/framework/_unit_utils.py
torchtnt/framework/auto_unit.py
torchtnt/framework/callback.py
torchtnt/framework/evaluate.py
torchtnt/framework/fit.py
torchtnt/framework/predict.py
torchtnt/framework/state.py
torchtnt/framework/train.py
torchtnt/framework/unit.py
torchtnt/framework/utils.py
torchtnt/framework/callbacks/__init__.py
torchtnt/framework/callbacks/_checkpoint_utils.py
torchtnt/framework/callbacks/base_checkpointer.py
torchtnt/framework/callbacks/base_csv_writer.py
torchtnt/framework/callbacks/checkpointer_types.py
torchtnt/framework/callbacks/dcp_saver.py
torchtnt/framework/callbacks/early_stopping.py
torchtnt/framework/callbacks/empty_cuda_cache.py
torchtnt/framework/callbacks/garbage_collector.py
torchtnt/framework/callbacks/iteration_time_logger.py
torchtnt/framework/callbacks/lambda_callback.py
torchtnt/framework/callbacks/learning_rate_monitor.py
torchtnt/framework/callbacks/memory_snapshot.py
torchtnt/framework/callbacks/module_summary.py
torchtnt/framework/callbacks/progress_reporter.py
torchtnt/framework/callbacks/pytorch_profiler.py
torchtnt/framework/callbacks/slow_rank_detector.py
torchtnt/framework/callbacks/system_resources_monitor.py
torchtnt/framework/callbacks/tensorboard_parameter_monitor.py
torchtnt/framework/callbacks/throughput_logger.py
torchtnt/framework/callbacks/time_limit_interrupter.py
torchtnt/framework/callbacks/time_wait_for_batch_logger.py
torchtnt/framework/callbacks/torch_compile.py
torchtnt/framework/callbacks/torchsnapshot_saver.py
torchtnt/framework/callbacks/tqdm_progress_bar.py
torchtnt/framework/callbacks/train_progress_monitor.py
torchtnt/utils/__init__.py
torchtnt/utils/checkpoint.py
torchtnt/utils/device.py
torchtnt/utils/distributed.py
torchtnt/utils/early_stop_checker.py
torchtnt/utils/env.py
torchtnt/utils/flops.py
torchtnt-0.2.4.dist-info/LICENSE
torchtnt-0.2.4.dist-info/METADATA
torchtnt-0.2.4.dist-info/WHEEL
torchtnt-0.2.4.dist-info/top_level.txt
torchtnt-0.2.4.dist-info/zip-safe
torchtnt-0.2.4.dist-info/RECORD
